MANIFEST.in
README.md
VERSION
setup.cfg
setup.py
slalom.dataops.egg-info/PKG-INFO
slalom.dataops.egg-info/SOURCES.txt
slalom.dataops.egg-info/dependency_links.txt
slalom.dataops.egg-info/entry_points.txt
slalom.dataops.egg-info/requires.txt
slalom.dataops.egg-info/top_level.txt
slalom/dataops/__init__.py
slalom/dataops/anon.py
slalom/dataops/env.py
slalom/dataops/infra.py
slalom/dataops/jobs.py
slalom/dataops/pandasutils.py
slalom/dataops/sparkutils.py