Metadata-Version: 2.1
Name: slalom.dataops
Version: 2.0.0.124
Summary: Slalom GGP libary for DataOps automation
Home-page: https://bitbucket.org/slalom-consulting/dataops-tools/
Author: Aaron (AJ) Steers
Author-email: aj.steers@slalom.com
License: MIT
Download-URL: https://github.com/slalom-ggp/dataops-tools/archive/v_0.1.tar.gz
Keywords: DATAOPS,SLALOM,DATA,AUTOMATION,CI/CD,DEVOPS
Platform: UNKNOWN
Classifier: Development Status :: 4 - Beta
Classifier: Intended Audience :: Developers
Classifier: Topic :: Software Development :: Build Tools
Classifier: License :: OSI Approved :: MIT License
Classifier: Programming Language :: Python :: 3.7
Provides-Extra: AWS
Provides-Extra: S3
Provides-Extra: Azure
Provides-Extra: Pandas
Provides-Extra: Spark
